LICENSE
MANIFEST.in
README.md
setup.py
portalmessenger/__init__.py
portalmessenger/__main__.py
portalmessenger/callbacks.py
portalmessenger/db.py
portalmessenger/message.py
portalmessenger/schema.sql
portalmessenger/settings.py
portalmessenger/views.py
portalmessenger/websockets.py
portalmessenger.egg-info/PKG-INFO
portalmessenger.egg-info/SOURCES.txt
portalmessenger.egg-info/dependency_links.txt
portalmessenger.egg-info/requires.txt
portalmessenger.egg-info/top_level.txt
portalmessenger/modem/__init__.py
portalmessenger/modem/basemodem.py
portalmessenger/modem/demomodem.py
portalmessenger/modem/js8callmodem.py
portalmessenger/modem/__pycache__/__init__.cpython-311.pyc
portalmessenger/modem/__pycache__/basemodem.cpython-311.pyc
portalmessenger/modem/__pycache__/demomodem.cpython-311.pyc
portalmessenger/modem/__pycache__/js8callmodem.cpython-311.pyc
portalmessenger/static/bootstrap.min.css
portalmessenger/static/chat.js
portalmessenger/static/common.js
portalmessenger/static/dark.css
portalmessenger/static/fontawesome.min.css
portalmessenger/static/jquery-ui.min.css
portalmessenger/static/jquery-ui.min.js
portalmessenger/static/jquery-ui.structure.min.css
portalmessenger/static/jquery-ui.theme.min.css
portalmessenger/static/jquery.min.js
portalmessenger/static/large-font.css
portalmessenger/static/media.css
portalmessenger/static/network.js
portalmessenger/static/socket.io.min.js
portalmessenger/static/stations.js
portalmessenger/static/styles.css
portalmessenger/static/icons/add-solid.svg
portalmessenger/static/icons/arrow-left.svg
portalmessenger/static/icons/chat-hollow.svg
portalmessenger/static/icons/chat-solid.svg
portalmessenger/static/icons/delete-hollow.svg
portalmessenger/static/icons/double_arrow.svg
portalmessenger/static/icons/dropdown-arrow.svg
portalmessenger/static/icons/error.svg
portalmessenger/static/icons/gear-hollow.svg
portalmessenger/static/icons/gear-solid.svg
portalmessenger/static/icons/hamburger.svg
portalmessenger/static/icons/list-hollow.svg
portalmessenger/static/icons/list-solid.svg
portalmessenger/static/icons/loading.svg
portalmessenger/static/icons/lock-small.svg
portalmessenger/static/icons/portalmessenger.icns
