Metadata-Version: 2.1
Name: portalmessenger
Version: 0.1.0
Summary: HF radio messaging web app using pyjs8call
Home-page: https://github.com/simplyequipped/portalmessenger
Author: Simply Equipped LLC
Author-email: howard@simplyequipped.com
Classifier: Programming Language :: Python :: 3
Classifier: License :: OSI Approved :: MIT License
Classifier: Operating System :: OS Independent
Requires-Python: >=3.7.1
License-File: LICENSE
Requires-Dist: pyjs8call>=0.2.3
Requires-Dist: flask>=3.0.0
Requires-Dist: flask-socketio>=5.3.3
Requires-Dist: pyshortcuts>=1.9.0
